multimodal_files/__init__.py
multimodal_files/dependency_requirements.py
multimodal_files/file_conversion.py
multimodal_files/core/__init__.py
multimodal_files/core/audio_file.py
multimodal_files/core/image_file.py
multimodal_files/core/multimodal_file.py
multimodal_files/core/video_file.py
multimodal_files-0.0.0.dist-info/LICENSE
multimodal_files-0.0.0.dist-info/METADATA
multimodal_files-0.0.0.dist-info/WHEEL
multimodal_files-0.0.0.dist-info/top_level.txt
multimodal_files-0.0.0.dist-info/RECORD
