Metadata-Version: 2.1
Name: multimodal-files
Version: 0.0.0
Summary: Web-ready standardized file processing and serialization. Read, load and convert to standard file types with a common interface.
Author: SocAIty
License: GPLv3
Project-URL: Repository, https://github.com/SocAIty/multimodal-files
Requires-Python: >=3.8
License-File: LICENSE
Requires-Dist: numpy >=1.18.0
Requires-Dist: opencv-python >=4.2
Requires-Dist: soundfile >=0.12.0
Provides-Extra: audiofile
Requires-Dist: numpy >=1.18.0 ; extra == 'audiofile'
Requires-Dist: soundfile >=0.12.0 ; extra == 'audiofile'
Provides-Extra: imagefile
Requires-Dist: numpy >=1.18.0 ; extra == 'imagefile'
Requires-Dist: opencv-python >=4.2 ; extra == 'imagefile'
Provides-Extra: full
Requires-Dist: numpy >=1.18.0 ; extra == 'full'
Requires-Dist: opencv-python >=4.2 ; extra == 'full'
Requires-Dist: soundfile >=0.12.0 ; extra == 'full'
